mwauth/__init__.py
mwauth/base_auth.py
mwauth/baseuser.py
mwauth/basic_auth.py
mwauth/kong_auth.py
mwauth/redis_session.py
mwauth/session_auth.py
mwauth/session_auth2.py
mwauth/session_auth3.py
mwauth/utils.py
mwauth/static/auth/css/bootstrap.min.css
mwauth/static/auth/css/bootstrap.min.css.map
mwauth/static/auth/css/font-awesome.css
mwauth/static/auth/css/login.css
mwauth/static/auth/fonts/fontawesome-webfont.eot
mwauth/static/auth/fonts/fontawesome-webfont.ttf
mwauth/static/auth/fonts/fontawesome-webfont.woff
mwauth/static/auth/fonts/fontawesome-webfont.woff2
mwauth/static/auth/fonts/glyphicons-halflings-regular.eot
mwauth/static/auth/fonts/glyphicons-halflings-regular.svg
mwauth/static/auth/fonts/glyphicons-halflings-regular.ttf
mwauth/static/auth/fonts/glyphicons-halflings-regular.woff
mwauth/static/auth/fonts/glyphicons-halflings-regular.woff2
mwauth/static/auth/js/bootstrap.min.js
mwauth/static/auth/js/jquery.js
mwauth/static/auth/js/md5-jquery.js
mwauth/static/auth/js/md5.js
mwauth/templates/auth/login.html
mwauth-0.4.51.dist-info/licenses/LICENSE.txt
mwauth-0.4.51.dist-info/METADATA
mwauth-0.4.51.dist-info/WHEEL
mwauth-0.4.51.dist-info/top_level.txt
mwauth-0.4.51.dist-info/RECORD
