Metadata-Version: 2.4
Name: mwauth
Version: 0.4.51
Summary: maxwin auth
Home-page: https://bitbucket.org/maxwin-inc/auth/src
Author: cxhjet
Author-email: cxhjet@qq.com
Project-URL: Bug Reports, https://bitbucket.org/maxwin-inc/auth/issues?status=new&status=open
Project-URL: Funding, https://donate.pypi.org
Project-URL: Say Thanks!, http://saythanks.io/to/example
Project-URL: Source, https://bitbucket.org/maxwin-inc/auth/src
Keywords: maxwin commonlib auth
Classifier: Development Status :: 3 - Alpha
Classifier: Intended Audience :: Developers
Classifier: Topic :: Software Development :: Build Tools
Classifier: License :: OSI Approved :: MIT License
Classifier: Programming Language :: Python :: 3.5
Classifier: Programming Language :: Python :: 3.6
Classifier: Programming Language :: Python :: 3.7
Classifier: Programming Language :: Python :: 3.8
Classifier: Programming Language :: Python :: 3.9
License-File: LICENSE.txt
Requires-Dist: flask>=0.11.1
Dynamic: author
Dynamic: author-email
Dynamic: classifier
Dynamic: description-content-type
Dynamic: home-page
Dynamic: keywords
Dynamic: license-file
Dynamic: project-url
Dynamic: requires-dist
Dynamic: summary
